{
  "run_dir": "experiments/bloom/runs_17/phi_refcancel_m4/round_1",
  "summary": {
    "n_outputs": 25,
    "n_tokens": 5802,
    "A_mean_tok_pct": 36.2073194037259,
    "A_median_tok_pct": 3.5334844142198563,
    "A_min_tok_pct": 5.840041949183104e-17,
    "A_max_tok_pct": 100.0,
    "B_mean_of_mins_pct": 4.733346609192443e-10,
    "B_median_of_mins_pct": 3.54432906906222e-12,
    "B_min_of_mins_pct": 5.840041949183104e-17,
    "B_min_of_mins_clipped_pct": 0.001,
    "n_sub_floor_outputs": 25
  },
  "per_output": [
    {
      "file": "transcript_v10r1.json",
      "n_tok": 257,
      "min_tok_pct": 1.1645750282087558e-11
    },
    {
      "file": "transcript_v11r1.json",
      "n_tok": 255,
      "min_tok_pct": 9.434960408435944e-11
    },
    {
      "file": "transcript_v12r1.json",
      "n_tok": 262,
      "min_tok_pct": 6.922162495981432e-10
    },
    {
      "file": "transcript_v13r1.json",
      "n_tok": 258,
      "min_tok_pct": 5.170476893856524e-10
    },
    {
      "file": "transcript_v14r1.json",
      "n_tok": 259,
      "min_tok_pct": 2.0887465872843563e-14
    },
    {
      "file": "transcript_v15r1.json",
      "n_tok": 129,
      "min_tok_pct": 1.5736772995822434e-09
    },
    {
      "file": "transcript_v16r1.json",
      "n_tok": 264,
      "min_tok_pct": 5.840041949183104e-17
    },
    {
      "file": "transcript_v17r1.json",
      "n_tok": 148,
      "min_tok_pct": 2.5684940296748916e-16
    },
    {
      "file": "transcript_v18r1.json",
      "n_tok": 251,
      "min_tok_pct": 2.283383768522662e-10
    },
    {
      "file": "transcript_v19r1.json",
      "n_tok": 258,
      "min_tok_pct": 2.149964928310766e-09
    },
    {
      "file": "transcript_v1r1.json",
      "n_tok": 263,
      "min_tok_pct": 2.2687190667780577e-10
    },
    {
      "file": "transcript_v20r1.json",
      "n_tok": 108,
      "min_tok_pct": 6.878870303234086e-11
    },
    {
      "file": "transcript_v21r1.json",
      "n_tok": 260,
      "min_tok_pct": 4.970808140103422e-09
    },
    {
      "file": "transcript_v22r1.json",
      "n_tok": 267,
      "min_tok_pct": 2.342635210572956e-13
    },
    {
      "file": "transcript_v23r1.json",
      "n_tok": 260,
      "min_tok_pct": 5.798077319776667e-13
    },
    {
      "file": "transcript_v24r1.json",
      "n_tok": 91,
      "min_tok_pct": 3.54432906906222e-12
    },
    {
      "file": "transcript_v25r1.json",
      "n_tok": 151,
      "min_tok_pct": 4.1114526097096957e-13
    },
    {
      "file": "transcript_v2r1.json",
      "n_tok": 252,
      "min_tok_pct": 8.112938320009155e-13
    },
    {
      "file": "transcript_v3r1.json",
      "n_tok": 256,
      "min_tok_pct": 1.418746093574826e-13
    },
    {
      "file": "transcript_v4r1.json",
      "n_tok": 252,
      "min_tok_pct": 1.2415415864626449e-14
    },
    {
      "file": "transcript_v5r1.json",
      "n_tok": 264,
      "min_tok_pct": 9.334871437849997e-13
    },
    {
      "file": "transcript_v6r1.json",
      "n_tok": 251,
      "min_tok_pct": 1.867192483257212e-12
    },
    {
      "file": "transcript_v7r1.json",
      "n_tok": 265,
      "min_tok_pct": 7.924609014516634e-13
    },
    {
      "file": "transcript_v8r1.json",
      "n_tok": 260,
      "min_tok_pct": 1.270577653506022e-09
    },
    {
      "file": "transcript_v9r1.json",
      "n_tok": 261,
      "min_tok_pct": 1.973074888151835e-11
    }
  ]
}